{
  "default": "pharos-atlantic",
  "x402Version": 1,
  "scheme": "escrow",
  "networks": {
    "pharos-atlantic": {
      "chainId": 688689,
      "name": "Pharos Atlantic Testnet",
      "rpc": "https://atlantic.dplabs-internal.com",
      "explorer": "https://atlantic.pharosscan.xyz",
      "nativeCurrency": "PHRS",
      "x402Network": "eip155:688689",
      "faucet": "https://testnet.pharosnetwork.xyz",
      "contracts": {
        "escrow": "",
        "reputation": "",
        "arbiter": "",
        "usdc": ""
      },
      "note": "Fill in `contracts` after running contracts/script/Deploy.s.sol against this RPC."
    },
    "local": {
      "chainId": 688689,
      "name": "Local anvil (anvil --chain-id 688689)",
      "rpc": "http://localhost:8545",
      "explorer": "",
      "nativeCurrency": "PHRS",
      "x402Network": "eip155:688689",
      "contracts": {
        "escrow": "0x9fE46736679d2D9a65F0992F2272dE9f3c7fa6e0",
        "reputation": "0xe7f1725E7734CE288F8367e1Bb143E90bb3F0512",
        "arbiter": "0xCf7Ed3AccA5a467e9e704C703E8D87F634fB0Fc9",
        "usdc": "0x5FbDB2315678afecb367f032d93F642f64180aa3"
      },
      "note": "Deterministic addresses for a fresh anvil deploying Deploy.s.sol from the default account (nonces 0-3). Reproducible; used by the verified local quickstart."
    }
  }
}
